lianyhaii/TimeSeries_FE.py
lianyhaii/__init__.py
lianyhaii/base_model.py
lianyhaii/eda_tool.py
lianyhaii/fe_selector.py
lianyhaii/feature_tools.py
lianyhaii/metrics.py
lianyhaii/model.py
lianyhaii/reg_model.py
lianyhaii/tools.py
lianyhaii/ts_model.py
lianyhaii/__pycache__/TimeSeries_FE.cpython-37.pyc
lianyhaii/__pycache__/__init__.cpython-37.pyc
lianyhaii/__pycache__/eda_tool.cpython-37.pyc
lianyhaii/__pycache__/fe_selector.cpython-37.pyc
lianyhaii/__pycache__/feature_tools.cpython-37.pyc
lianyhaii/__pycache__/metrics.cpython-37.pyc
lianyhaii/__pycache__/model.cpython-37.pyc
lianyhaii/__pycache__/reg_model.cpython-37.pyc
lianyhaii/__pycache__/tools.cpython-37.pyc
lianyhaii/__pycache__/ts_model.cpython-37.pyc
lianyhaii-0.0.143.dist-info/LICENSE
lianyhaii-0.0.143.dist-info/METADATA
lianyhaii-0.0.143.dist-info/WHEEL
lianyhaii-0.0.143.dist-info/top_level.txt
lianyhaii-0.0.143.dist-info/RECORD
