Metadata-Version: 2.1
Name: lianyhaii
Version: 0.0.143
Summary: A package to win data competition
Home-page: https://github.com/Ernnnn/lianyhaii
Author: Ernnnn
Author-email: lianyhai@163.com
License: UNKNOWN
Platform: UNKNOWN
Classifier: Programming Language :: Python :: 3
Classifier: License :: OSI Approved :: MIT License
Classifier: Operating System :: OS Independent
Requires-Python: >=3.6
License-File: LICENSE
Requires-Dist: scikit-learn
Requires-Dist: optuna
Requires-Dist: plotly
Requires-Dist: catboost
Requires-Dist: xgboost
Requires-Dist: lightgbm
Requires-Dist: seaborn
Requires-Dist: pyarrow
Requires-Dist: gensim
Requires-Dist: pathos
